Pos   Hex Data           Description or Code
------------------------------------------------------------------------
0000                     ** source chunk: mrClean.clf
                         ** global header start **
0000  1B4C7561           header signature: "\27Lua"
0004  50                 version (major:minor hex digits)
0005  01                 endianness (1=little endian)
0006  04                 size of int (bytes)
0007  04                 size of size_t (bytes)
0008  04                 size of Instruction (bytes)
0009  06                 size of OP (bits)
000A  08                 size of A (bits)
000B  09                 size of B (bits)
000C  09                 size of C (bits)
000D  08                 size of number (bytes)
000E  B6099368E7F57D41   sample number (double)
                         * x86 standard (32-bit, little endian, doubles)
                         ** global header end **
                         
0016                     ** function [0] definition (level 1)
                         ** start of function **
0016  0D000000           string size (13)
001A  406D72436C65616E+  "@mrClean"
0022  2E6C756100         ".lua\0"
                         source name: @mrClean.lua
0027  00000000           line defined (0)
002B  00                 nups (0)
002C  00                 numparams (0)
002D  00                 is_vararg (0)
002E  0E                 maxstacksize (14)
                         * lines:
002F  9B000000           sizelineinfo (155)
                         [pc] (line)
0033  0C000000           [001] (12)
0037  0C000000           [002] (12)
003B  0C000000           [003] (12)
003F  0C000000           [004] (12)
0043  0C000000           [005] (12)
0047  0C000000           [006] (12)
004B  0C000000           [007] (12)
004F  0C000000           [008] (12)
0053  0D000000           [009] (13)
0057  0D000000           [010] (13)
005B  0D000000           [011] (13)
005F  0F000000           [012] (15)
0063  0F000000           [013] (15)
0067  0F000000           [014] (15)
006B  11000000           [015] (17)
006F  11000000           [016] (17)
0073  11000000           [017] (17)
0077  13000000           [018] (19)
007B  13000000           [019] (19)
007F  13000000           [020] (19)
0083  15000000           [021] (21)
0087  15000000           [022] (21)
008B  15000000           [023] (21)
008F  16000000           [024] (22)
0093  16000000           [025] (22)
0097  16000000           [026] (22)
009B  16000000           [027] (22)
009F  16000000           [028] (22)
00A3  16000000           [029] (22)
00A7  16000000           [030] (22)
00AB  16000000           [031] (22)
00AF  16000000           [032] (22)
00B3  17000000           [033] (23)
00B7  17000000           [034] (23)
00BB  26000000           [035] (38)
00BF  26000000           [036] (38)
00C3  19000000           [037] (25)
00C7  46000000           [038] (70)
00CB  46000000           [039] (70)
00CF  28000000           [040] (40)
00D3  5A000000           [041] (90)
00D7  5A000000           [042] (90)
00DB  7C000000           [043] (124)
00DF  7C000000           [044] (124)
00E3  7F000000           [045] (127)
00E7  7F000000           [046] (127)
00EB  7F000000           [047] (127)
00EF  80000000           [048] (128)
00F3  82000000           [049] (130)
00F7  83000000           [050] (131)
00FB  83000000           [051] (131)
00FF  83000000           [052] (131)
0103  83000000           [053] (131)
0107  84000000           [054] (132)
010B  84000000           [055] (132)
010F  84000000           [056] (132)
0113  84000000           [057] (132)
0117  84000000           [058] (132)
011B  84000000           [059] (132)
011F  85000000           [060] (133)
0123  82000000           [061] (130)
0127  82000000           [062] (130)
012B  88000000           [063] (136)
012F  88000000           [064] (136)
0133  88000000           [065] (136)
0137  88000000           [066] (136)
013B  88000000           [067] (136)
013F  88000000           [068] (136)
0143  88000000           [069] (136)
0147  88000000           [070] (136)
014B  88000000           [071] (136)
014F  8A000000           [072] (138)
0153  8A000000           [073] (138)
0157  8B000000           [074] (139)
015B  8B000000           [075] (139)
015F  8B000000           [076] (139)
0163  8B000000           [077] (139)
0167  8B000000           [078] (139)
016B  8C000000           [079] (140)
016F  8C000000           [080] (140)
0173  8C000000           [081] (140)
0177  8C000000           [082] (140)
017B  8D000000           [083] (141)
017F  8D000000           [084] (141)
0183  8E000000           [085] (142)
0187  8E000000           [086] (142)
018B  8E000000           [087] (142)
018F  8E000000           [088] (142)
0193  8E000000           [089] (142)
0197  8E000000           [090] (142)
019B  8E000000           [091] (142)
019F  8E000000           [092] (142)
01A3  8E000000           [093] (142)
01A7  8E000000           [094] (142)
01AB  8E000000           [095] (142)
01AF  8E000000           [096] (142)
01B3  8E000000           [097] (142)
01B7  91000000           [098] (145)
01BB  91000000           [099] (145)
01BF  91000000           [100] (145)
01C3  92000000           [101] (146)
01C7  92000000           [102] (146)
01CB  93000000           [103] (147)
01CF  93000000           [104] (147)
01D3  93000000           [105] (147)
01D7  93000000           [106] (147)
01DB  93000000           [107] (147)
01DF  96000000           [108] (150)
01E3  96000000           [109] (150)
01E7  97000000           [110] (151)
01EB  97000000           [111] (151)
01EF  98000000           [112] (152)
01F3  98000000           [113] (152)
01F7  98000000           [114] (152)
01FB  98000000           [115] (152)
01FF  98000000           [116] (152)
0203  98000000           [117] (152)
0207  98000000           [118] (152)
020B  99000000           [119] (153)
020F  99000000           [120] (153)
0213  99000000           [121] (153)
0217  99000000           [122] (153)
021B  99000000           [123] (153)
021F  99000000           [124] (153)
0223  99000000           [125] (153)
0227  99000000           [126] (153)
022B  99000000           [127] (153)
022F  99000000           [128] (153)
0233  99000000           [129] (153)
0237  9A000000           [130] (154)
023B  9A000000           [131] (154)
023F  9A000000           [132] (154)
0243  9A000000           [133] (154)
0247  9C000000           [134] (156)
024B  9C000000           [135] (156)
024F  9C000000           [136] (156)
0253  9C000000           [137] (156)
0257  9F000000           [138] (159)
025B  9F000000           [139] (159)
025F  A0000000           [140] (160)
0263  A0000000           [141] (160)
0267  A0000000           [142] (160)
026B  A2000000           [143] (162)
026F  A2000000           [144] (162)
0273  A2000000           [145] (162)
0277  A2000000           [146] (162)
027B  A3000000           [147] (163)
027F  A3000000           [148] (163)
0283  A3000000           [149] (163)
0287  A3000000           [150] (163)
028B  A3000000           [151] (163)
028F  A3000000           [152] (163)
0293  A3000000           [153] (163)
0297  A3000000           [154] (163)
029B  A4000000           [155] (164)
                         * locals:
029F  09000000           sizelocvars (9)
02A3  06000000           string size (6)
02A7  77696E333200       "win32"
                         local [0]: win32
02AD  22000000             startpc (34)
02B1  9A000000             endpc   (154)
02B5  0D000000           string size (13)
02B9  52656D6F76655549+  "RemoveUI"
02C1  6C65737300         "less\0"
                         local [1]: RemoveUIless
02C6  28000000             startpc (40)
02CA  9A000000             endpc   (154)
02CE  10000000           string size (16)
02D2  52656D6F7665496E+  "RemoveIn"
02DA  7374616C6C657200   "staller\0"
                         local [2]: RemoveInstaller
02E2  2A000000             startpc (42)
02E6  9A000000             endpc   (154)
02EA  09000000           string size (9)
02EE  7761697454696D65+  "waitTime"
02F6  00                 "\0"
                         local [3]: waitTime
02F7  2F000000             startpc (47)
02FB  9A000000             endpc   (154)
02FF  06000000           string size (6)
0303  6D7574657800       "mutex"
                         local [4]: mutex
0309  30000000             startpc (48)
030D  9A000000             endpc   (154)
0311  0D000000           string size (13)
0315  696E7374616C6C65+  "installe"
031D  724C6F6300         "rLoc\0"
                         local [5]: installerLoc
0322  4E000000             startpc (78)
0326  8D000000             endpc   (141)
032A  08000000           string size (8)
032E  7375636365737300   "success"
                         local [6]: success
0336  64000000             startpc (100)
033A  8D000000             endpc   (141)
033E  04000000           string size (4)
0342  65727200           "err"
                         local [7]: err
0346  64000000             startpc (100)
034A  8D000000             endpc   (141)
034E  0B000000           string size (11)
0352  65727248616E646C+  "errHandl"
035A  657200             "er\0"
                         local [8]: errHandler
035D  6F000000             startpc (111)
0361  84000000             endpc   (132)
                         * upvalues:
0365  00000000           sizeupvalues (0)
                         * constants:
0369  2E000000           sizek (46)
036D  04                 const type 4
036E  03000000           string size (3)
0372  696F00             "io"
                         const [0]: "io"
0375  04                 const type 4
0376  07000000           string size (7)
037A  6F757470757400     "output"
                         const [1]: "output"
0381  04                 const type 4
0382  05000000           string size (5)
0386  6F70656E00         "open"
                         const [2]: "open"
038B  04                 const type 4
038C  11000000           string size (17)
0390  2E2E5C756E696E73+  "..\\unins"
0398  744C6F672E747874+  "tLog.txt"
03A0  00                 "\0"
                         const [3]: "..\\uninstLog.txt"
03A1  04                 const type 4
03A2  02000000           string size (2)
03A6  6100               "a"
                         const [4]: "a"
03A8  04                 const type 4
03A9  07000000           string size (7)
03AD  646F66696C6500     "dofile"
                         const [5]: "dofile"
03B4  04                 const type 4
03B5  0F000000           string size (15)
03B9  636F6D7061742D35+  "compat-5"
03C1  2E312E6C756100     ".1.lua\0"
                         const [6]: "compat-5.1.lua"
03C8  04                 const type 4
03C9  08000000           string size (8)
03CD  7265717569726500   "require"
                         const [7]: "require"
03D5  04                 const type 4
03D6  07000000           string size (7)
03DA  6C7561636F6D00     "luacom"
                         const [8]: "luacom"
03E1  04                 const type 4
03E2  11000000           string size (17)
03E6  7261696E7374616C+  "rainstal"
03EE  6C65727061746873+  "lerpaths"
03F6  00                 "\0"
                         const [9]: "rainstallerpaths"
03F7  04                 const type 4
03F8  0B000000           string size (11)
03FC  636F6E6669672E6C+  "config.l"
0404  756100             "ua\0"
                         const [10]: "config.lua"
0407  04                 const type 4
0408  05000000           string size (5)
040C  626C6F6200         "blob"
                         const [11]: "blob"
0411  04                 const type 4
0412  06000000           string size (6)
0416  777269746500       "write"
                         const [12]: "write"
041C  04                 const type 4
041D  02000000           string size (2)
0421  0A00               "\n"
                         const [13]: "\n"
0423  04                 const type 4
0424  03000000           string size (3)
0428  6F7300             "os"
                         const [14]: "os"
042B  04                 const type 4
042C  05000000           string size (5)
0430  6461746500         "date"
                         const [15]: "date"
0435  04                 const type 4
0436  04000000           string size (4)
043A  25632000           "%c "
                         const [16]: "%c "
043E  04                 const type 4
043F  0C000000           string size (12)
0443  4C6F616465642062+  "Loaded b"
044B  6C6F6200           "lob\0"
                         const [17]: "Loaded blob"
044F  04                 const type 4
0450  0D000000           string size (13)
0454  57696E3332496E74+  "Win32Int"
045C  65726F7000         "erop\0"
                         const [18]: "Win32Interop"
0461  04                 const type 4
0462  13000000           string size (19)
0466  74727952656D6F76+  "tryRemov"
046E  6547616D6573526F+  "eGamesRo"
0476  6F7400             "ot\0"
                         const [19]: "tryRemoveGamesRoot"
0479  04                 const type 4
047A  17000000           string size (23)
047E  72656D6F76654B6E+  "removeKn"
0486  6F776E53746F7265+  "ownStore"
048E  46726F6E747300     "Fronts\0"
                         const [20]: "removeKnownStoreFronts"
0495  04                 const type 4
0496  06000000           string size (6)
049A  636C6F636B00       "clock"
                         const [21]: "clock"
04A0  04                 const type 4
04A1  06000000           string size (6)
04A5  4D7574657800       "Mutex"
                         const [22]: "Mutex"
04AB  04                 const type 4
04AC  13000000           string size (19)
04B0  5241435632496E73+  "RACV2Ins"
04B8  74616C6C6572496E+  "tallerIn"
04C0  737400             "st\0"
                         const [23]: "RACV2InstallerInst"
04C3  03                 const type 3
04C4  0000000000004E40   const [24]: (60)
04CC  04                 const type 4
04CD  10000000           string size (16)
04D1  52756E6E696E6720+  "Running "
04D9  4D72436C65616E00   "MrClean\0"
                         const [25]: "Running MrClean"
04E1  04                 const type 4
04E2  0F000000           string size (15)
04E6  4765745265674B65+  "GetRegKe"
04EE  7956616C756500     "yValue\0"
                         const [26]: "GetRegKeyValue"
04F5  04                 const type 4
04F6  13000000           string size (19)
04FA  484B45595F4C4F43+  "HKEY_LOC"
0502  414C5F4D41434849+  "AL_MACHI"
050A  4E4500             "NE\0"
                         const [27]: "HKEY_LOCAL_MACHINE"
050D  04                 const type 4
050E  21000000           string size (33)
0512  534F465457415245+  "SOFTWARE"
051A  5C47616D65496E73+  "\\GameIns"
0522  74616C6C65725C49+  "taller\\I"
052A  6E7374616C6C6572+  "nstaller"
0532  00                 "\0"
                         const [28]: "SOFTWARE\\GameInstaller\\Installer"
0533  04                 const type 4
0534  09000000           string size (9)
0538  4C6F636174696F6E+  "Location"
0540  00                 "\0"
                         const [29]: "Location"
0541  04                 const type 4
0542  01000000           string size (1)
0546  00                 ""
                         const [30]: ""
0547  04                 const type 4
0548  0C000000           string size (12)
054C  675F636F6E737461+  "g_consta"
0554  6E747300           "nts\0"
                         const [31]: "g_constants"
0558  04                 const type 4
0559  0D000000           string size (13)
055D  696E7374616C6C65+  "installe"
0565  724C6F6300         "rLoc\0"
                         const [32]: "installerLoc"
056A  04                 const type 4
056B  0F000000           string size (15)
056F  696E7374616C6C65+  "installe"
0577  724C6F633A2000     "rLoc: \0"
                         const [33]: "installerLoc: "
057E  04                 const type 4
057F  09000000           string size (9)
0583  746F737472696E67+  "tostring"
058B  00                 "\0"
                         const [34]: "tostring"
058C  04                 const type 4
058D  06000000           string size (6)
0591  7063616C6C00       "pcall"
                         const [35]: "pcall"
0597  04                 const type 4
0598  0D000000           string size (13)
059C  4572726F7248616E+  "ErrorHan"
05A4  646C657200         "dler\0"
                         const [36]: "ErrorHandler"
05A9  04                 const type 4
05AA  1C000000           string size (28)
05AE  0A556E696E737461+  "\nUninsta"
05B6  6C6C6174696F6E20+  "llation "
05BE  4661696C65642121+  "Failed!!"
05C6  212C2000           "!, \0"
                         const [37]: "\nUninstallation Failed!!!, "
05CA  04                 const type 4
05CB  0B000000           string size (11)
05CF  4C6F674D65737361+  "LogMessa"
05D7  676500             "ge\0"
                         const [38]: "LogMessage"
05DA  04                 const type 4
05DB  1B000000           string size (27)
05DF  556E696E7374616C+  "Uninstal"
05E7  6C6174696F6E2046+  "lation F"
05EF  61696C6564212121+  "ailed!!!"
05F7  2C2000             ", \0"
                         const [39]: "Uninstallation Failed!!!, "
05FA  04                 const type 4
05FB  0C000000           string size (12)
05FF  48616E646C654572+  "HandleEr"
0607  726F7200           "ror\0"
                         const [40]: "HandleError"
060B  04                 const type 4
060C  1A000000           string size (26)
0610  0A556E696E737461+  "\nUninsta"
0618  6C6C6174696F6E20+  "llation "
0620  436F6D706C657465+  "Complete"
0628  2100               "!\0"
                         const [41]: "\nUninstallation Complete!"
062A  04                 const type 4
062B  08000000           string size (8)
062F  52656C6561736500   "Release"
                         const [42]: "Release"
0637  04                 const type 4
0638  06000000           string size (6)
063C  436C6F736500       "Close"
                         const [43]: "Close"
0642  04                 const type 4
0643  3E000000           string size (62)
0647  0A556E61626C6520+  "\nUnable "
064F  746F206F62746169+  "to obtai"
0657  6E206D757465782E+  "n mutex."
065F  20436F756C646E27+  " Couldn'"
0667  7420756E696E7374+  "t uninst"
066F  616C6C20636C6965+  "all clie"
0677  6E746C6573732066+  "ntless f"
067F  696C65732E00       "iles.\0"
                         const [44]: "\nUnable to obtain mutex. Couldn't uninstall clientless files."
0685  04                 const type 4
0686  50000000           string size (80)
068A  556E61626C652074+  "Unable t"
0692  6F206F627461696E+  "o obtain"
069A  205241435632496E+  " RACV2In"
06A2  7374616C6C657249+  "stallerI"
06AA  6E7374206D757465+  "nst mute"
06B2  782E20436F756C64+  "x. Could"
06BA  6E277420756E696E+  "n't unin"
06C2  7374616C6C20636C+  "stall cl"
06CA  69656E746C657373+  "ientless"
06D2  2066696C65732E00   " files.\0"
                         const [45]: "Unable to obtain RACV2InstallerInst mutex. Couldn't uninstall clientless files."
                         * functions:
06DA  04000000           sizep (4)
                         
06DE                     ** function [0] definition (level 2)
                         ** start of function **
06DE  00000000           string size (0)
                         source name: (none)
06E2  19000000           line defined (25)
06E6  01                 nups (1)
06E7  02                 numparams (2)
06E8  00                 is_vararg (0)
06E9  09                 maxstacksize (9)
                         * lines:
06EA  45000000           sizelineinfo (69)
                         [pc] (line)
06EE  1A000000           [01] (26)
06F2  1A000000           [02] (26)
06F6  1A000000           [03] (26)
06FA  1A000000           [04] (26)
06FE  1A000000           [05] (26)
0702  1A000000           [06] (26)
0706  1A000000           [07] (26)
070A  1A000000           [08] (26)
070E  1A000000           [09] (26)
0712  1A000000           [10] (26)
0716  1A000000           [11] (26)
071A  1B000000           [12] (27)
071E  1B000000           [13] (27)
0722  1B000000           [14] (27)
0726  1B000000           [15] (27)
072A  1B000000           [16] (27)
072E  1B000000           [17] (27)
0732  1B000000           [18] (27)
0736  1B000000           [19] (27)
073A  1C000000           [20] (28)
073E  1C000000           [21] (28)
0742  1C000000           [22] (28)
0746  1C000000           [23] (28)
074A  1C000000           [24] (28)
074E  1C000000           [25] (28)
0752  1D000000           [26] (29)
0756  1D000000           [27] (29)
075A  1D000000           [28] (29)
075E  1D000000           [29] (29)
0762  1D000000           [30] (29)
0766  1D000000           [31] (29)
076A  1F000000           [32] (31)
076E  1F000000           [33] (31)
0772  1F000000           [34] (31)
0776  1F000000           [35] (31)
077A  1F000000           [36] (31)
077E  1F000000           [37] (31)
0782  20000000           [38] (32)
0786  20000000           [39] (32)
078A  20000000           [40] (32)
078E  20000000           [41] (32)
0792  20000000           [42] (32)
0796  20000000           [43] (32)
079A  20000000           [44] (32)
079E  20000000           [45] (32)
07A2  20000000           [46] (32)
07A6  21000000           [47] (33)
07AA  21000000           [48] (33)
07AE  21000000           [49] (33)
07B2  21000000           [50] (33)
07B6  21000000           [51] (33)
07BA  21000000           [52] (33)
07BE  21000000           [53] (33)
07C2  21000000           [54] (33)
07C6  21000000           [55] (33)
07CA  22000000           [56] (34)
07CE  24000000           [57] (36)
07D2  24000000           [58] (36)
07D6  24000000           [59] (36)
07DA  24000000           [60] (36)
07DE  24000000           [61] (36)
07E2  24000000           [62] (36)
07E6  24000000           [63] (36)
07EA  24000000           [64] (36)
07EE  24000000           [65] (36)
07F2  24000000           [66] (36)
07F6  24000000           [67] (36)
07FA  24000000           [68] (36)
07FE  26000000           [69] (38)
                         * locals:
0802  04000000           sizelocvars (4)
0806  0B000000           string size (11)
080A  73746F726566726F+  "storefro"
0812  6E7400             "nt\0"
                         local [0]: storefront
0815  00000000             startpc (0)
0819  44000000             endpc   (68)
081D  08000000           string size (8)
0821  76657273696F6E00   "version"
                         local [1]: version
0829  00000000             startpc (0)
082D  44000000             endpc   (68)
0831  0A000000           string size (10)
0835  67616D6573526F6F+  "gamesRoo"
083D  7400               "t\0"
                         local [2]: gamesRoot
083F  0B000000             startpc (11)
0843  44000000             endpc   (68)
0847  04000000           string size (4)
084B  6D736700           "msg"
                         local [3]: msg
084F  25000000             startpc (37)
0853  37000000             endpc   (55)
                         * upvalues:
0857  01000000           sizeupvalues (1)
085B  06000000           string size (6)
085F  77696E333200       "win32"
                         upvalue [0]: win32
                         * constants:
0865  18000000           sizek (24)
0869  04                 const type 4
086A  0F000000           string size (15)
086E  4765745265674B65+  "GetRegKe"
0876  7956616C756500     "yValue\0"
                         const [0]: "GetRegKeyValue"
087D  04                 const type 4
087E  12000000           string size (18)
0882  484B45595F434C41+  "HKEY_CLA"
088A  535345535F524F4F+  "SSES_ROO"
0892  5400               "T\0"
                         const [1]: "HKEY_CLASSES_ROOT"
0894  04                 const type 4
0895  0B000000           string size (11)
0899  5C536F6674776172+  "\\Softwar"
08A1  655C00             "e\\\0"
                         const [2]: "\\Software\\"
08A4  04                 const type 4
08A5  02000000           string size (2)
08A9  5C00               "\\"
                         const [3]: "\\"
08AB  04                 const type 4
08AC  0D000000           string size (13)
08B0  5C50726566657265+  "\\Prefere"
08B8  6E63657300         "nces\0"
                         const [4]: "\\Preferences"
08BD  04                 const type 4
08BE  0A000000           string size (10)
08C2  47616D6573526F6F+  "GamesRoo"
08CA  7400               "t\0"
                         const [5]: "GamesRoot"
08CC  04                 const type 4
08CD  07000000           string size (7)
08D1  737472696E6700     "string"
                         const [6]: "string"
08D8  04                 const type 4
08D9  04000000           string size (4)
08DD  6C656E00           "len"
                         const [7]: "len"
08E1  03                 const type 3
08E2  0000000000000000   const [8]: (0)
08EA  04                 const type 4
08EB  0E000000           string size (14)
08EF  466F6C6465724973+  "FolderIs"
08F7  456D70747900       "Empty\0"
                         const [9]: "FolderIsEmpty"
08FD  04                 const type 4
08FE  06000000           string size (6)
0902  7063616C6C00       "pcall"
                         const [10]: "pcall"
0908  04                 const type 4
0909  0B000000           string size (11)
090D  44656C6574654669+  "DeleteFi"
0915  6C6500             "le\0"
                         const [11]: "DeleteFile"
0918  04                 const type 4
0919  08000000           string size (8)
091D  4C65617665202200   "Leave \""
                         const [12]: "Leave \""
0925  04                 const type 4
0926  09000000           string size (9)
092A  746F737472696E67+  "tostring"
0932  00                 "\0"
                         const [13]: "tostring"
0933  04                 const type 4
0934  15000000           string size (21)
0938  2220617320697420+  "\" as it "
0940  6973206E6F742065+  "is not e"
0948  6D70747900         "mpty\0"
                         const [14]: "\" as it is not empty"
094D  04                 const type 4
094E  03000000           string size (3)
0952  696F00             "io"
                         const [15]: "io"
0955  04                 const type 4
0956  06000000           string size (6)
095A  777269746500       "write"
                         const [16]: "write"
0960  04                 const type 4
0961  02000000           string size (2)
0965  0A00               "\n"
                         const [17]: "\n"
0967  04                 const type 4
0968  03000000           string size (3)
096C  6F7300             "os"
                         const [18]: "os"
096F  04                 const type 4
0970  05000000           string size (5)
0974  6461746500         "date"
                         const [19]: "date"
0979  04                 const type 4
097A  04000000           string size (4)
097E  25632000           "%c "
                         const [20]: "%c "
0982  04                 const type 4
0983  0B000000           string size (11)
0987  4C6F674D65737361+  "LogMessa"
098F  676500             "ge\0"
                         const [21]: "LogMessage"
0992  04                 const type 4
0993  19000000           string size (25)
0997  47616D6573526F6F+  "GamesRoo"
099F  74206E6F7420666F+  "t not fo"
09A7  756E6420666F7220+  "und for "
09AF  00                 "\0"
                         const [22]: "GamesRoot not found for "
09B0  04                 const type 4
09B1  0A000000           string size (10)
09B5  2076657273696F6E+  " version"
09BD  2000               " \0"
                         const [23]: " version "
                         * functions:
09BF  00000000           sizep (0)
                         * code:
09C3  45000000           sizecode (69)
09C7  04000002           [01] getupval   2   0        ; win32
09CB  863E0102           [02] gettable   2   2   250  ; "GetRegKeyValue"
09CF  41000003           [03] loadk      3   1        ; "HKEY_CLASSES_ROOT"
09D3  81000004           [04] loadk      4   2        ; "\\Software\\"
09D7  00000005           [05] move       5   0      
09DB  C1000006           [06] loadk      6   3        ; "\\"
09DF  00800007           [07] move       7   1      
09E3  01010008           [08] loadk      8   4        ; "\\Preferences"
09E7  13020204           [09] concat     4   4   8  
09EB  41010005           [10] loadk      5   5        ; "GamesRoot"
09EF  99000202           [11] call       2   4   2  
09F3  18000102           [12] test       2   2   0    ; to [14] if true
09F7  940A8000           [13] jmp        43           ; to [57]
09FB  85010003           [14] getglobal  3   6        ; string
09FF  46C00103           [15] gettable   3   3   257  ; "len"
0A03  00000104           [16] move       4   2      
0A07  99000103           [17] call       3   2   2  
0A0B  D6008100           [18] lt         0   258 3    ; 0, to [20] if true
0A0F  14098000           [19] jmp        37           ; to [57]
0A13  04000003           [20] getupval   3   0        ; win32
0A17  C6C00103           [21] gettable   3   3   259  ; "FolderIsEmpty"
0A1B  00000104           [22] move       4   2      
0A1F  99000103           [23] call       3   2   2  
0A23  18800103           [24] test       3   3   0    ; to [26] if true
0A27  54018000           [25] jmp        6            ; to [32]
0A2B  85020003           [26] getglobal  3   10       ; pcall
0A2F  04000004           [27] getupval   4   0        ; win32
0A33  46410204           [28] gettable   4   4   261  ; "DeleteFile"
0A37  00000105           [29] move       5   2      
0A3B  59800103           [30] call       3   3   1  
0A3F  14098000           [31] jmp        37           ; to [69]
0A43  01030003           [32] loadk      3   12       ; "Leave \""
0A47  45030004           [33] getglobal  4   13       ; tostring
0A4B  00000105           [34] move       5   2      
0A4F  99000104           [35] call       4   2   2  
0A53  81030005           [36] loadk      5   14       ; "\" as it is not empty"
0A57  53810103           [37] concat     3   3   5  
0A5B  C5030004           [38] getglobal  4   15       ; io
0A5F  86420204           [39] gettable   4   4   266  ; "write"
0A63  41040005           [40] loadk      5   17       ; "\n"
0A67  85040006           [41] getglobal  6   18       ; os
0A6B  46430306           [42] gettable   6   6   269  ; "date"
0A6F  01050007           [43] loadk      7   20       ; "%c "
0A73  99000106           [44] call       6   2   2  
0A77  00800107           [45] move       7   3      
0A7B  59000204           [46] call       4   4   1  
0A7F  04000004           [47] getupval   4   0        ; win32
0A83  C6430204           [48] gettable   4   4   271  ; "LogMessage"
0A87  85040005           [49] getglobal  5   18       ; os
0A8B  46C30205           [50] gettable   5   5   269  ; "date"
0A8F  01050006           [51] loadk      6   20       ; "%c "
0A93  99000105           [52] call       5   2   2  
0A97  00800106           [53] move       6   3      
0A9B  93810205           [54] concat     5   5   6  
0A9F  59000104           [55] call       4   2   1  
0AA3  D4028000           [56] jmp        12           ; to [69]
0AA7  04000003           [57] getupval   3   0        ; win32
0AAB  C6C30103           [58] gettable   3   3   271  ; "LogMessage"
0AAF  85040004           [59] getglobal  4   18       ; os
0AB3  46430204           [60] gettable   4   4   269  ; "date"
0AB7  01050005           [61] loadk      5   20       ; "%c "
0ABB  99000104           [62] call       4   2   2  
0ABF  81050005           [63] loadk      5   22       ; "GamesRoot not found for "
0AC3  00000006           [64] move       6   0      
0AC7  C1050007           [65] loadk      7   23       ; " version "
0ACB  00800008           [66] move       8   1      
0ACF  13020204           [67] concat     4   4   8  
0AD3  59000103           [68] call       3   2   1  
0AD7  1B800000           [69] return     0   1      
                         ** end of function **

                         
0ADB                     ** function [1] definition (level 2)
                         ** start of function **
0ADB  00000000           string size (0)
                         source name: (none)
0ADF  28000000           line defined (40)
0AE3  01                 nups (1)
0AE4  00                 numparams (0)
0AE5  00                 is_vararg (0)
0AE6  09                 maxstacksize (9)
                         * lines:
0AE7  83000000           sizelineinfo (131)
                         [pc] (line)
0AEB  29000000           [001] (41)
0AEF  29000000           [002] (41)
0AF3  29000000           [003] (41)
0AF7  29000000           [004] (41)
0AFB  29000000           [005] (41)
0AFF  29000000           [006] (41)
0B03  2A000000           [007] (42)
0B07  2A000000           [008] (42)
0B0B  2A000000           [009] (42)
0B0F  2A000000           [010] (42)
0B13  2A000000           [011] (42)
0B17  2B000000           [012] (43)
0B1B  2C000000           [013] (44)
0B1F  2C000000           [014] (44)
0B23  2C000000           [015] (44)
0B27  2C000000           [016] (44)
0B2B  2D000000           [017] (45)
0B2F  2E000000           [018] (46)
0B33  2F000000           [019] (47)
0B37  2F000000           [020] (47)
0B3B  2F000000           [021] (47)
0B3F  2F000000           [022] (47)
0B43  2F000000           [023] (47)
0B47  2F000000           [024] (47)
0B4B  30000000           [025] (48)
0B4F  30000000           [026] (48)
0B53  30000000           [027] (48)
0B57  30000000           [028] (48)
0B5B  30000000           [029] (48)
0B5F  30000000           [030] (48)
0B63  30000000           [031] (48)
0B67  30000000           [032] (48)
0B6B  30000000           [033] (48)
0B6F  30000000           [034] (48)
0B73  31000000           [035] (49)
0B77  31000000           [036] (49)
0B7B  31000000           [037] (49)
0B7F  31000000           [038] (49)
0B83  31000000           [039] (49)
0B87  31000000           [040] (49)
0B8B  31000000           [041] (49)
0B8F  31000000           [042] (49)
0B93  31000000           [043] (49)
0B97  31000000           [044] (49)
0B9B  32000000           [045] (50)
0B9F  32000000           [046] (50)
0BA3  32000000           [047] (50)
0BA7  32000000           [048] (50)
0BAB  33000000           [049] (51)
0BAF  33000000           [050] (51)
0BB3  33000000           [051] (51)
0BB7  33000000           [052] (51)
0BBB  34000000           [053] (52)
0BBF  34000000           [054] (52)
0BC3  34000000           [055] (52)
0BC7  34000000           [056] (52)
0BCB  34000000           [057] (52)
0BCF  34000000           [058] (52)
0BD3  34000000           [059] (52)
0BD7  34000000           [060] (52)
0BDB  36000000           [061] (54)
0BDF  2D000000           [062] (45)
0BE3  2D000000           [063] (45)
0BE7  38000000           [064] (56)
0BEB  38000000           [065] (56)
0BEF  39000000           [066] (57)
0BF3  3A000000           [067] (58)
0BF7  3A000000           [068] (58)
0BFB  3A000000           [069] (58)
0BFF  3A000000           [070] (58)
0C03  3A000000           [071] (58)
0C07  3A000000           [072] (58)
0C0B  3A000000           [073] (58)
0C0F  3A000000           [074] (58)
0C13  3A000000           [075] (58)
0C17  3B000000           [076] (59)
0C1B  3B000000           [077] (59)
0C1F  3B000000           [078] (59)
0C23  3B000000           [079] (59)
0C27  3B000000           [080] (59)
0C2B  3B000000           [081] (59)
0C2F  3B000000           [082] (59)
0C33  3B000000           [083] (59)
0C37  3B000000           [084] (59)
0C3B  3C000000           [085] (60)
0C3F  3D000000           [086] (61)
0C43  3D000000           [087] (61)
0C47  3E000000           [088] (62)
0C4B  3F000000           [089] (63)
0C4F  3F000000           [090] (63)
0C53  3F000000           [091] (63)
0C57  3F000000           [092] (63)
0C5B  3F000000           [093] (63)
0C5F  3F000000           [094] (63)
0C63  3F000000           [095] (63)
0C67  3F000000           [096] (63)
0C6B  3F000000           [097] (63)
0C6F  40000000           [098] (64)
0C73  40000000           [099] (64)
0C77  40000000           [100] (64)
0C7B  40000000           [101] (64)
0C7F  40000000           [102] (64)
0C83  40000000           [103] (64)
0C87  40000000           [104] (64)
0C8B  40000000           [105] (64)
0C8F  40000000           [106] (64)
0C93  40000000           [107] (64)
0C97  42000000           [108] (66)
0C9B  42000000           [109] (66)
0C9F  42000000           [110] (66)
0CA3  42000000           [111] (66)
0CA7  42000000           [112] (66)
0CAB  43000000           [113] (67)
0CAF  43000000           [114] (67)
0CB3  43000000           [115] (67)
0CB7  43000000           [116] (67)
0CBB  43000000           [117] (67)
0CBF  43000000           [118] (67)
0CC3  43000000           [119] (67)
0CC7  43000000           [120] (67)
0CCB  43000000           [121] (67)
0CCF  44000000           [122] (68)
0CD3  44000000           [123] (68)
0CD7  44000000           [124] (68)
0CDB  44000000           [125] (68)
0CDF  44000000           [126] (68)
0CE3  44000000           [127] (68)
0CE7  44000000           [128] (68)
0CEB  44000000           [129] (68)
0CEF  44000000           [130] (68)
0CF3  46000000           [131] (70)
                         * locals:
0CF7  07000000           sizelocvars (7)
0CFB  10000000           string size (16)
0CFF  6D756C74694C696E+  "multiLin"
0D07  65537472696E6700   "eString\0"
                         local [0]: multiLineString
0D0F  06000000             startpc (6)
0D13  82000000             endpc   (130)
0D17  06000000           string size (6)
0D1B  696E64657800       "index"
                         local [1]: index
0D21  0C000000             startpc (12)
0D25  54000000             endpc   (84)
0D29  06000000           string size (6)
0D2D  636F756E7400       "count"
                         local [2]: count
0D33  10000000             startpc (16)
0D37  54000000             endpc   (84)
0D3B  05000000           string size (5)
0D3F  6C696E6500         "line"
                         local [3]: line
0D44  12000000             startpc (18)
0D48  3D000000             endpc   (61)
0D4C  04000000           string size (4)
0D50  6D736700           "msg"
                         local [4]: msg
0D54  42000000             startpc (66)
0D58  54000000             endpc   (84)
0D5C  04000000           string size (4)
0D60  6D736700           "msg"
                         local [5]: msg
0D64  58000000             startpc (88)
0D68  6A000000             endpc   (106)
0D6C  04000000           string size (4)
0D70  6D736700           "msg"
                         local [6]: msg
0D74  70000000             startpc (112)
0D78  82000000             endpc   (130)
                         * upvalues:
0D7C  01000000           sizeupvalues (1)
0D80  06000000           string size (6)
0D84  77696E333200       "win32"
                         upvalue [0]: win32
                         * constants:
0D8A  1E000000           sizek (30)
0D8E  04                 const type 4
0D8F  16000000           string size (22)
0D93  5265675175657279+  "RegQuery"
0D9B  4D756C744C696E65+  "MultLine"
0DA3  56616C756500       "Value\0"
                         const [0]: "RegQueryMultLineValue"
0DA9  04                 const type 4
0DAA  13000000           string size (19)
0DAE  484B45595F4C4F43+  "HKEY_LOC"
0DB6  414C5F4D41434849+  "AL_MACHI"
0DBE  4E4500             "NE\0"
                         const [1]: "HKEY_LOCAL_MACHINE"
0DC1  04                 const type 4
0DC2  21000000           string size (33)
0DC6  534F465457415245+  "SOFTWARE"
0DCE  5C47616D65496E73+  "\\GameIns"
0DD6  74616C6C65725C49+  "taller\\I"
0DDE  6E7374616C6C6572+  "nstaller"
0DE6  00                 "\0"
                         const [2]: "SOFTWARE\\GameInstaller\\Installer"
0DE7  04                 const type 4
0DE8  0C000000           string size (12)
0DEC  53746F726566726F+  "Storefro"
0DF4  6E747300           "nts\0"
                         const [3]: "Storefronts"
0DF8  04                 const type 4
0DF9  06000000           string size (6)
0DFD  7461626C6500       "table"
                         const [4]: "table"
0E03  04                 const type 4
0E04  05000000           string size (5)
0E08  7479706500         "type"
                         const [5]: "type"
0E0D  03                 const type 3
0E0E  000000000000F03F   const [6]: (1)
0E16  04                 const type 4
0E17  05000000           string size (5)
0E1B  6765746E00         "getn"
                         const [7]: "getn"
0E20  04                 const type 4
0E21  07000000           string size (7)
0E25  737472696E6700     "string"
                         const [8]: "string"
0E2C  04                 const type 4
0E2D  04000000           string size (4)
0E31  6C656E00           "len"
                         const [9]: "len"
0E35  04                 const type 4
0E36  03000000           string size (3)
0E3A  696F00             "io"
                         const [10]: "io"
0E3D  04                 const type 4
0E3E  06000000           string size (6)
0E42  777269746500       "write"
                         const [11]: "write"
0E48  04                 const type 4
0E49  02000000           string size (2)
0E4D  0A00               "\n"
                         const [12]: "\n"
0E4F  04                 const type 4
0E50  03000000           string size (3)
0E54  6F7300             "os"
                         const [13]: "os"
0E57  04                 const type 4
0E58  05000000           string size (5)
0E5C  6461746500         "date"
                         const [14]: "date"
0E61  04                 const type 4
0E62  04000000           string size (4)
0E66  25632000           "%c "
                         const [15]: "%c "
0E6A  04                 const type 4
0E6B  13000000           string size (19)
0E6F  53746F726566726F+  "Storefro"
0E77  6E7420666F756E64+  "nt found"
0E7F  3A2000             ": \0"
                         const [16]: "Storefront found: "
0E82  04                 const type 4
0E83  0B000000           string size (11)
0E87  4C6F674D65737361+  "LogMessa"
0E8F  676500             "ge\0"
                         const [17]: "LogMessage"
0E92  04                 const type 4
0E93  13000000           string size (19)
0E97  74727952656D6F76+  "tryRemov"
0E9F  6547616D6573526F+  "eGamesRo"
0EA7  6F7400             "ot\0"
                         const [18]: "tryRemoveGamesRoot"
0EAA  04                 const type 4
0EAB  04000000           string size (4)
0EAF  312E3000           "1.0"
                         const [19]: "1.0"
0EB3  04                 const type 4
0EB4  04000000           string size (4)
0EB8  322E3000           "2.0"
                         const [20]: "2.0"
0EBC  04                 const type 4
0EBD  0E000000           string size (14)
0EC1  52656744656C6574+  "RegDelet"
0EC9  655472656500       "eTree\0"
                         const [21]: "RegDeleteTree"
0ECF  04                 const type 4
0ED0  12000000           string size (18)
0ED4  484B45595F434C41+  "HKEY_CLA"
0EDC  535345535F524F4F+  "SSES_ROO"
0EE4  5400               "T\0"
                         const [22]: "HKEY_CLASSES_ROOT"
0EE6  04                 const type 4
0EE7  0C000000           string size (12)
0EEB  675F636F6E737461+  "g_consta"
0EF3  6E747300           "nts\0"
                         const [23]: "g_constants"
0EF7  04                 const type 4
0EF8  08000000           string size (8)
0EFC  626173656B657900   "basekey"
                         const [24]: "basekey"
0F04  03                 const type 3
0F05  0000000000000000   const [25]: (0)
0F0D  04                 const type 4
0F0E  23000000           string size (35)
0F12  53746F726566726F+  "Storefro"
0F1A  6E7473204E4F5420+  "nts NOT "
0F22  466F756E6420696E+  "Found in"
0F2A  2072656769737472+  " registr"
0F32  792E00             "y.\0"
                         const [26]: "Storefronts NOT Found in registry."
0F35  00                 const type 0
                         const [27]: nil
0F36  04                 const type 4
0F37  22000000           string size (34)
0F3B  53746F726566726F+  "Storefro"
0F43  6E7473204E4F5420+  "nts NOT "
0F4B  466F756E6420696E+  "Found in"
0F53  2072656769737472+  " registr"
0F5B  7900               "y\0"
                         const [28]: "Storefronts NOT Found in registry"
0F5D  04                 const type 4
0F5E  22000000           string size (34)
0F62  5265675175657279+  "RegQuery"
0F6A  4D756C744C696E65+  "MultLine"
0F72  56616C7565207265+  "Value re"
0F7A  7475726E65642061+  "turned a"
0F82  2000               " \0"
                         const [29]: "RegQueryMultLineValue returned a "
                         * functions:
0F84  00000000           sizep (0)
                         * code:
0F88  83000000           sizecode (131)
0F8C  04000000           [001] getupval   0   0        ; win32
0F90  863E0000           [002] gettable   0   0   250  ; "RegQueryMultLineValue"
0F94  41000001           [003] loadk      1   1        ; "HKEY_LOCAL_MACHINE"
0F98  81000002           [004] loadk      2   2        ; "SOFTWARE\\GameInstaller\\Installer"
0F9C  C1000003           [005] loadk      3   3        ; "Storefronts"
0FA0  99000200           [006] call       0   4   2  
0FA4  45010001           [007] getglobal  1   5        ; type
0FA8  00000002           [008] move       2   0      
0FAC  99000101           [009] call       1   2   2  
0FB0  55007F00           [010] eq         0   254 1    ; "table", to [12] if true
0FB4  54128000           [011] jmp        74           ; to [86]
0FB8  81010001           [012] loadk      1   6        ; 1
0FBC  05010002           [013] getglobal  2   4        ; table
0FC0  46400102           [014] gettable   2   2   257  ; "getn"
0FC4  00000003           [015] move       3   0      
0FC8  99000102           [016] call       2   2   2  
0FCC  D40A8000           [017] jmp        44           ; to [62]
0FD0  46000003           [018] gettable   3   0   1  
0FD4  05020004           [019] getglobal  4   8        ; string
0FD8  C6400204           [020] gettable   4   4   259  ; "len"
0FDC  00800105           [021] move       5   3      
0FE0  99000104           [022] call       4   2   2  
0FE4  16018000           [023] lt         0   256 4    ; 1, to [25] if true
0FE8  D4088000           [024] jmp        36           ; to [61]
0FEC  85020004           [025] getglobal  4   10       ; io
0FF0  46410204           [026] gettable   4   4   261  ; "write"
0FF4  01030005           [027] loadk      5   12       ; "\n"
0FF8  45030006           [028] getglobal  6   13       ; os
0FFC  06420306           [029] gettable   6   6   264  ; "date"
1000  C1030007           [030] loadk      7   15       ; "%c "
1004  99000106           [031] call       6   2   2  
1008  01040007           [032] loadk      7   16       ; "Storefront found: "
100C  00800108           [033] move       8   3      
1010  59800204           [034] call       4   5   1  
1014  04000004           [035] getupval   4   0        ; win32
1018  C6420204           [036] gettable   4   4   267  ; "LogMessage"
101C  45030005           [037] getglobal  5   13       ; os
1020  06C20205           [038] gettable   5   5   264  ; "date"
1024  C1030006           [039] loadk      6   15       ; "%c "
1028  99000105           [040] call       5   2   2  
102C  01040006           [041] loadk      6   16       ; "Storefront found: "
1030  00800107           [042] move       7   3      
1034  D3810205           [043] concat     5   5   7  
1038  59000104           [044] call       4   2   1  
103C  85040004           [045] getglobal  4   18       ; tryRemoveGamesRoot
1040  00800105           [046] move       5   3      
1044  C1040006           [047] loadk      6   19       ; "1.0"
1048  59800104           [048] call       4   3   1  
104C  85040004           [049] getglobal  4   18       ; tryRemoveGamesRoot
1050  00800105           [050] move       5   3      
1054  01050006           [051] loadk      6   20       ; "2.0"
1058  59800104           [052] call       4   3   1  
105C  04000004           [053] getupval   4   0        ; win32
1060  C6430204           [054] gettable   4   4   271  ; "RegDeleteTree"
1064  81050005           [055] loadk      5   22       ; "HKEY_CLASSES_ROOT"
1068  C5050006           [056] getglobal  6   23       ; g_constants
106C  86440306           [057] gettable   6   6   274  ; "basekey"
1070  00800107           [058] move       7   3      
1074  D3010306           [059] concat     6   6   7  
1078  59800104           [060] call       4   3   1  
107C  0CC00001           [061] add        1   1   256  ; 1
1080  97800001           [062] le         1   1   2    ; to [64] if false
1084  54F47F00           [063] jmp        -46          ; to [18]
1088  95808900           [064] eq         0   275 2    ; 0, to [66] if true
108C  14108000           [065] jmp        65           ; to [131]
1090  81060003           [066] loadk      3   26       ; "Storefronts NOT Found in registry."
1094  85020004           [067] getglobal  4   10       ; io
1098  46410204           [068] gettable   4   4   261  ; "write"
109C  01030005           [069] loadk      5   12       ; "\n"
10A0  45030006           [070] getglobal  6   13       ; os
10A4  06420306           [071] gettable   6   6   264  ; "date"
10A8  C1030007           [072] loadk      7   15       ; "%c "
10AC  99000106           [073] call       6   2   2  
10B0  00800107           [074] move       7   3      
10B4  59000204           [075] call       4   4   1  
10B8  04000004           [076] getupval   4   0        ; win32
10BC  C6420204           [077] gettable   4   4   267  ; "LogMessage"
10C0  45030005           [078] getglobal  5   13       ; os
10C4  06C20205           [079] gettable   5   5   264  ; "date"
10C8  C1030006           [080] loadk      6   15       ; "%c "
10CC  99000105           [081] call       5   2   2  
10D0  00800106           [082] move       6   3      
10D4  93810205           [083] concat     5   5   6  
10D8  59000104           [084] call       4   2   1  
10DC  140B8000           [085] jmp        45           ; to [131]
10E0  15808A00           [086] eq         0   277 0    ; nil, to [88] if true
10E4  D4048000           [087] jmp        20           ; to [108]
10E8  01070001           [088] loadk      1   28       ; "Storefronts NOT Found in registry"
10EC  85020002           [089] getglobal  2   10       ; io
10F0  46410102           [090] gettable   2   2   261  ; "write"
10F4  01030003           [091] loadk      3   12       ; "\n"
10F8  45030004           [092] getglobal  4   13       ; os
10FC  06420204           [093] gettable   4   4   264  ; "date"
1100  C1030005           [094] loadk      5   15       ; "%c "
1104  99000104           [095] call       4   2   2  
1108  00800005           [096] move       5   1      
110C  59000202           [097] call       2   4   1  
1110  04000002           [098] getupval   2   0        ; win32
1114  C6420102           [099] gettable   2   2   267  ; "LogMessage"
1118  45030003           [100] getglobal  3   13       ; os
111C  06C20103           [101] gettable   3   3   264  ; "date"
1120  C1030004           [102] loadk      4   15       ; "%c "
1124  99000103           [103] call       3   2   2  
1128  00800004           [104] move       4   1      
112C  13810103           [105] concat     3   3   4  
1130  59000102           [106] call       2   2   1  
1134  94058000           [107] jmp        23           ; to [131]
1138  41070001           [108] loadk      1   29       ; "RegQueryMultLineValue returned a "
113C  45010002           [109] getglobal  2   5        ; type
1140  00000003           [110] move       3   0      
1144  99000102           [111] call       2   2   2  
1148  93800001           [112] concat     1   1   2  
114C  85020002           [113] getglobal  2   10       ; io
1150  46410102           [114] gettable   2   2   261  ; "write"
1154  01030003           [115] loadk      3   12       ; "\n"
1158  45030004           [116] getglobal  4   13       ; os
115C  06420204           [117] gettable   4   4   264  ; "date"
1160  C1030005           [118] loadk      5   15       ; "%c "
1164  99000104           [119] call       4   2   2  
1168  00800005           [120] move       5   1      
116C  59000202           [121] call       2   4   1  
1170  04000002           [122] getupval   2   0        ; win32
1174  C6420102           [123] gettable   2   2   267  ; "LogMessage"
1178  45030003           [124] getglobal  3   13       ; os
117C  06C20103           [125] gettable   3   3   264  ; "date"
1180  C1030004           [126] loadk      4   15       ; "%c "
1184  99000103           [127] call       3   2   2  
1188  00800004           [128] move       4   1      
118C  13810103           [129] concat     3   3   4  
1190  59000102           [130] call       2   2   1  
1194  1B800000           [131] return     0   1      
                         ** end of function **

                         
1198                     ** function [2] definition (level 2)
                         ** start of function **
1198  00000000           string size (0)
                         source name: (none)
119C  49000000           line defined (73)
11A0  01                 nups (1)
11A1  00                 numparams (0)
11A2  00                 is_vararg (0)
11A3  07                 maxstacksize (7)
                         * lines:
11A4  29000000           sizelineinfo (41)
                         [pc] (line)
11A8  4C000000           [01] (76)
11AC  4C000000           [02] (76)
11B0  4C000000           [03] (76)
11B4  4C000000           [04] (76)
11B8  4D000000           [05] (77)
11BC  4D000000           [06] (77)
11C0  4D000000           [07] (77)
11C4  4F000000           [08] (79)
11C8  4F000000           [09] (79)
11CC  4F000000           [10] (79)
11D0  50000000           [11] (80)
11D4  51000000           [12] (81)
11D8  51000000           [13] (81)
11DC  52000000           [14] (82)
11E0  53000000           [15] (83)
11E4  53000000           [16] (83)
11E8  53000000           [17] (83)
11EC  53000000           [18] (83)
11F0  53000000           [19] (83)
11F4  53000000           [20] (83)
11F8  53000000           [21] (83)
11FC  53000000           [22] (83)
1200  53000000           [23] (83)
1204  54000000           [24] (84)
1208  54000000           [25] (84)
120C  54000000           [26] (84)
1210  54000000           [27] (84)
1214  54000000           [28] (84)
1218  54000000           [29] (84)
121C  55000000           [30] (85)
1220  55000000           [31] (85)
1224  55000000           [32] (85)
1228  55000000           [33] (85)
122C  57000000           [34] (87)
1230  57000000           [35] (87)
1234  57000000           [36] (87)
1238  52000000           [37] (82)
123C  52000000           [38] (82)
1240  52000000           [39] (82)
1244  59000000           [40] (89)
1248  5A000000           [41] (90)
                         * locals:
124C  04000000           sizelocvars (4)
1250  06000000           string size (6)
1254  6974656D7300       "items"
                         local [0]: items
125A  04000000             startpc (4)
125E  28000000             endpc   (40)
1262  05000000           string size (5)
1266  656E756D00         "enum"
                         local [1]: enum
126B  04000000             startpc (4)
126F  28000000             endpc   (40)
1273  08000000           string size (8)
1277  696E766F6B657200   "invoker"
                         local [2]: invoker
127F  0B000000             startpc (11)
1283  28000000             endpc   (40)
1287  07000000           string size (7)
128B  73637269707400     "script"
                         local [3]: script
1292  1D000000             startpc (29)
1296  21000000             endpc   (33)
                         * upvalues:
129A  01000000           sizeupvalues (1)
129E  06000000           string size (6)
12A2  77696E333200       "win32"
                         upvalue [0]: win32
                         * constants:
12A8  0E000000           sizek (14)
12AC  04                 const type 4
12AD  0F000000           string size (15)
12B1  476574466F6C6465+  "GetFolde"
12B9  724974656D7300     "rItems\0"
                         const [0]: "GetFolderItems"
12C0  04                 const type 4
12C1  0C000000           string size (12)
12C5  2E5C756E696E7374+  ".\\uninst"
12CD  616C6C00           "all\0"
                         const [1]: ".\\uninstall"
12D1  04                 const type 4
12D2  05000000           string size (5)
12D6  6974656D00         "item"
                         const [2]: "item"
12DB  04                 const type 4
12DC  05000000           string size (5)
12E0  4E65787400         "Next"
                         const [3]: "Next"
12E5  04                 const type 4
12E6  0A000000           string size (10)
12EA  675F696E766F6B65+  "g_invoke"
12F2  7200               "r\0"
                         const [4]: "g_invoker"
12F4  04                 const type 4
12F5  07000000           string size (7)
12F9  506172656E7400     "Parent"
                         const [5]: "Parent"
1300  04                 const type 4
1301  07000000           string size (7)
1305  737472696E6700     "string"
                         const [6]: "string"
130C  04                 const type 4
130D  05000000           string size (5)
1311  66696E6400         "find"
                         const [7]: "find"
1316  04                 const type 4
1317  05000000           string size (5)
131B  4E616D6500         "Name"
                         const [8]: "Name"
1320  04                 const type 4
1321  0C000000           string size (12)
1325  675F636F6E737461+  "g_consta"
132D  6E747300           "nts\0"
                         const [9]: "g_constants"
1331  04                 const type 4
1332  0A000000           string size (10)
1336  756E696E73744578+  "uninstEx"
133E  7400               "t\0"
                         const [10]: "uninstExt"
1340  04                 const type 4
1341  0C000000           string size (12)
1345  556E496E7374616C+  "UnInstal"
134D  6C657200           "ler\0"
                         const [11]: "UnInstaller"
1351  04                 const type 4
1352  0D000000           string size (13)
1356  2E5C756E696E7374+  ".\\uninst"
135E  616C6C5C00         "all\\\0"
                         const [12]: ".\\uninstall\\"
1363  04                 const type 4
1364  0E000000           string size (14)
1368  50726F6365737353+  "ProcessS"
1370  637269707400       "cript\0"
                         const [13]: "ProcessScript"
                         * functions:
1376  00000000           sizep (0)
                         * code:
137A  29000000           sizecode (41)
137E  04000000           [01] getupval   0   0        ; win32
1382  863E0000           [02] gettable   0   0   250  ; "GetFolderItems"
1386  41000001           [03] loadk      1   1        ; ".\\uninstall"
138A  D9000100           [04] call       0   2   3  
138E  58000000           [05] test       0   0   1    ; to [7] if false
1392  14008000           [06] jmp        1            ; to [8]
1396  1B800000           [07] return     0   1      
139A  4BBF0002           [08] self       2   1   253  ; "Next"
139E  99000102           [09] call       2   2   2  
13A2  87000002           [10] setglobal  2   2        ; item
13A6  05010002           [11] getglobal  2   4        ; g_invoker
13AA  41010003           [12] loadk      3   5        ; "Parent"
13AE  07010003           [13] setglobal  3   4        ; g_invoker
13B2  54058000           [14] jmp        22           ; to [37]
13B6  85010003           [15] getglobal  3   6        ; string
13BA  46C00103           [16] gettable   3   3   257  ; "find"
13BE  85000004           [17] getglobal  4   2        ; item
13C2  86400204           [18] gettable   4   4   258  ; "Name"
13C6  45020005           [19] getglobal  5   9        ; g_constants
13CA  06C10205           [20] gettable   5   5   260  ; "uninstExt"
13CE  99800103           [21] call       3   3   2  
13D2  18800103           [22] test       3   3   0    ; to [24] if true
13D6  54028000           [23] jmp        10           ; to [34]
13DA  C5020003           [24] getglobal  3   11       ; UnInstaller
13DE  01030004           [25] loadk      4   12       ; ".\\uninstall\\"
13E2  85000005           [26] getglobal  5   2        ; item
13E6  86C00205           [27] gettable   5   5   258  ; "Name"
13EA  53010204           [28] concat     4   4   5  
13EE  99000103           [29] call       3   2   2  
13F2  C6C10104           [30] gettable   4   3   263  ; "ProcessScript"
13F6  03800205           [31] loadnil    5   5      
13FA  02800006           [32] loadbool   6   1   0    ; true
13FE  59800104           [33] call       4   3   1  
1402  4BBF0003           [34] self       3   1   253  ; "Next"
1406  99000103           [35] call       3   2   2  
140A  87000003           [36] setglobal  3   2        ; item
140E  85000003           [37] getglobal  3   2        ; item
1412  58800103           [38] test       3   3   1    ; to [40] if false
1416  94F97F00           [39] jmp        -25          ; to [15]
141A  07010002           [40] setglobal  2   4        ; g_invoker
141E  1B800000           [41] return     0   1      
                         ** end of function **

                         
1422                     ** function [3] definition (level 2)
                         ** start of function **
1422  00000000           string size (0)
                         source name: (none)
1426  5C000000           line defined (92)
142A  01                 nups (1)
142B  00                 numparams (0)
142C  00                 is_vararg (0)
142D  0E                 maxstacksize (14)
                         * lines:
142E  8D000000           sizelineinfo (141)
                         [pc] (line)
1432  5E000000           [001] (94)
1436  5E000000           [002] (94)
143A  5E000000           [003] (94)
143E  5E000000           [004] (94)
1442  5E000000           [005] (94)
1446  5F000000           [006] (95)
144A  5F000000           [007] (95)
144E  60000000           [008] (96)
1452  60000000           [009] (96)
1456  60000000           [010] (96)
145A  60000000           [011] (96)
145E  60000000           [012] (96)
1462  64000000           [013] (100)
1466  64000000           [014] (100)
146A  64000000           [015] (100)
146E  64000000           [016] (100)
1472  64000000           [017] (100)
1476  64000000           [018] (100)
147A  64000000           [019] (100)
147E  64000000           [020] (100)
1482  64000000           [021] (100)
1486  65000000           [022] (101)
148A  65000000           [023] (101)
148E  65000000           [024] (101)
1492  65000000           [025] (101)
1496  65000000           [026] (101)
149A  65000000           [027] (101)
149E  65000000           [028] (101)
14A2  65000000           [029] (101)
14A6  65000000           [030] (101)
14AA  66000000           [031] (102)
14AE  66000000           [032] (102)
14B2  66000000           [033] (102)
14B6  66000000           [034] (102)
14BA  66000000           [035] (102)
14BE  66000000           [036] (102)
14C2  66000000           [037] (102)
14C6  66000000           [038] (102)
14CA  66000000           [039] (102)
14CE  66000000           [040] (102)
14D2  66000000           [041] (102)
14D6  66000000           [042] (102)
14DA  67000000           [043] (103)
14DE  67000000           [044] (103)
14E2  67000000           [045] (103)
14E6  67000000           [046] (103)
14EA  67000000           [047] (103)
14EE  67000000           [048] (103)
14F2  67000000           [049] (103)
14F6  68000000           [050] (104)
14FA  68000000           [051] (104)
14FE  68000000           [052] (104)
1502  68000000           [053] (104)
1506  68000000           [054] (104)
150A  68000000           [055] (104)
150E  68000000           [056] (104)
1512  68000000           [057] (104)
1516  68000000           [058] (104)
151A  68000000           [059] (104)
151E  68000000           [060] (104)
1522  68000000           [061] (104)
1526  6B000000           [062] (107)
152A  6B000000           [063] (107)
152E  6B000000           [064] (107)
1532  6B000000           [065] (107)
1536  6B000000           [066] (107)
153A  6B000000           [067] (107)
153E  6B000000           [068] (107)
1542  6D000000           [069] (109)
1546  6D000000           [070] (109)
154A  6D000000           [071] (109)
154E  6D000000           [072] (109)
1552  6D000000           [073] (109)
1556  6D000000           [074] (109)
155A  6D000000           [075] (109)
155E  6E000000           [076] (110)
1562  6E000000           [077] (110)
1566  6F000000           [078] (111)
156A  6F000000           [079] (111)
156E  6F000000           [080] (111)
1572  6F000000           [081] (111)
1576  70000000           [082] (112)
157A  70000000           [083] (112)
157E  71000000           [084] (113)
1582  71000000           [085] (113)
1586  71000000           [086] (113)
158A  71000000           [087] (113)
158E  71000000           [088] (113)
1592  71000000           [089] (113)
1596  71000000           [090] (113)
159A  71000000           [091] (113)
159E  72000000           [092] (114)
15A2  72000000           [093] (114)
15A6  72000000           [094] (114)
15AA  72000000           [095] (114)
15AE  72000000           [096] (114)
15B2  73000000           [097] (115)
15B6  73000000           [098] (115)
15BA  73000000           [099] (115)
15BE  73000000           [100] (115)
15C2  73000000           [101] (115)
15C6  73000000           [102] (115)
15CA  73000000           [103] (115)
15CE  74000000           [104] (116)
15D2  74000000           [105] (116)
15D6  74000000           [106] (116)
15DA  74000000           [107] (116)
15DE  74000000           [108] (116)
15E2  74000000           [109] (116)
15E6  75000000           [110] (117)
15EA  75000000           [111] (117)
15EE  75000000           [112] (117)
15F2  75000000           [113] (117)
15F6  75000000           [114] (117)
15FA  75000000           [115] (117)
15FE  75000000           [116] (117)
1602  75000000           [117] (117)
1606  75000000           [118] (117)
160A  75000000           [119] (117)
160E  75000000           [120] (117)
1612  75000000           [121] (117)
1616  76000000           [122] (118)
161A  76000000           [123] (118)
161E  76000000           [124] (118)
1622  76000000           [125] (118)
1626  76000000           [126] (118)
162A  76000000           [127] (118)
162E  76000000           [128] (118)
1632  76000000           [129] (118)
1636  78000000           [130] (120)
163A  78000000           [131] (120)
163E  78000000           [132] (120)
1642  78000000           [133] (120)
1646  78000000           [134] (120)
164A  78000000           [135] (120)
164E  78000000           [136] (120)
1652  78000000           [137] (120)
1656  78000000           [138] (120)
165A  7B000000           [139] (123)
165E  7B000000           [140] (123)
1662  7C000000           [141] (124)
                         * locals:
1666  07000000           sizelocvars (7)
166A  02000000           string size (2)
166E  7300               "s"
                         local [0]: s
1670  4B000000             startpc (75)
1674  8C000000             endpc   (140)
1678  04000000           string size (4)
167C  65727200           "err"
                         local [1]: err
1680  4B000000             startpc (75)
1684  8C000000             endpc   (140)
1688  08000000           string size (8)
168C  70726F634D677200   "procMgr"
                         local [2]: procMgr
1694  51000000             startpc (81)
1698  8A000000             endpc   (138)
169C  07000000           string size (7)
16A0  636F5061746800     "coPath"
                         local [3]: coPath
16A7  5B000000             startpc (91)
16AB  80000000             endpc   (128)
16AF  02000000           string size (2)
16B3  7300               "s"
                         local [4]: s
16B5  60000000             startpc (96)
16B9  80000000             endpc   (128)
16BD  02000000           string size (2)
16C1  6500               "e"
                         local [5]: e
16C3  60000000             startpc (96)
16C7  80000000             endpc   (128)
16CB  04000000           string size (4)
16CF  636D6400           "cmd"
                         local [6]: cmd
16D3  6D000000             startpc (109)
16D7  80000000             endpc   (128)
                         * upvalues:
16DB  01000000           sizeupvalues (1)
16DF  06000000           string size (6)
16E3  77696E333200       "win32"
                         upvalue [0]: win32
                         * constants:
16E9  2E000000           sizek (46)
16ED  04                 const type 4
16EE  0D000000           string size (13)
16F2  44656C6574655265+  "DeleteRe"
16FA  674B657900         "gKey\0"
                         const [0]: "DeleteRegKey"
16FF  04                 const type 4
1700  12000000           string size (18)
1704  484B45595F434C41+  "HKEY_CLA"
170C  535345535F524F4F+  "SSES_ROO"
1714  5400               "T\0"
                         const [1]: "HKEY_CLASSES_ROOT"
1716  04                 const type 4
1717  0E000000           string size (14)
171B  536F667477617265+  "Software"
1723  5C2E72676900       "\\.rgi\0"
                         const [2]: "Software\\.rgi"
1729  04                 const type 4
172A  17000000           string size (23)
172E  72656D6F76654B6E+  "removeKn"
1736  6F776E53746F7265+  "ownStore"
173E  46726F6E747300     "Fronts\0"
                         const [3]: "removeKnownStoreFronts"
1745  04                 const type 4
1746  0E000000           string size (14)
174A  52656744656C6574+  "RegDelet"
1752  655472656500       "eTree\0"
                         const [4]: "RegDeleteTree"
1758  04                 const type 4
1759  13000000           string size (19)
175D  484B45595F4C4F43+  "HKEY_LOC"
1765  414C5F4D41434849+  "AL_MACHI"
176D  4E4500             "NE\0"
                         const [5]: "HKEY_LOCAL_MACHINE"
1770  04                 const type 4
1771  17000000           string size (23)
1775  534F465457415245+  "SOFTWARE"
177D  5C47616D65496E73+  "\\GameIns"
1785  74616C6C657200     "taller\0"
                         const [6]: "SOFTWARE\\GameInstaller"
178C  04                 const type 4
178D  03000000           string size (3)
1791  696F00             "io"
                         const [7]: "io"
1794  04                 const type 4
1795  06000000           string size (6)
1799  777269746500       "write"
                         const [8]: "write"
179F  04                 const type 4
17A0  02000000           string size (2)
17A4  0A00               "\n"
                         const [9]: "\n"
17A6  04                 const type 4
17A7  03000000           string size (3)
17AB  6F7300             "os"
                         const [10]: "os"
17AE  04                 const type 4
17AF  05000000           string size (5)
17B3  6461746500         "date"
                         const [11]: "date"
17B8  04                 const type 4
17B9  04000000           string size (4)
17BD  25632000           "%c "
                         const [12]: "%c "
17C1  04                 const type 4
17C2  10000000           string size (16)
17C6  52656D6F7665496E+  "RemoveIn"
17CE  7374616C6C657200   "staller\0"
                         const [13]: "RemoveInstaller"
17D6  04                 const type 4
17D7  07000000           string size (7)
17DB  746D7044697200     "tmpDir"
                         const [14]: "tmpDir"
17E2  04                 const type 4
17E3  15000000           string size (21)
17E7  476574456E766972+  "GetEnvir"
17EF  6F6E6D656E745374+  "onmentSt"
17F7  72696E6700         "ring\0"
                         const [15]: "GetEnvironmentString"
17FC  04                 const type 4
17FD  05000000           string size (5)
1801  54454D5000         "TEMP"
                         const [16]: "TEMP"
1806  04                 const type 4
1807  04000000           string size (4)
180B  544D5000           "TMP"
                         const [17]: "TMP"
180F  04                 const type 4
1810  09000000           string size (9)
1814  746D704469723A20+  "tmpDir: "
181C  00                 "\0"
                         const [18]: "tmpDir: "
181D  04                 const type 4
181E  09000000           string size (9)
1822  746F737472696E67+  "tostring"
182A  00                 "\0"
                         const [19]: "tostring"
182B  04                 const type 4
182C  0A000000           string size (10)
1830  70726F6746696C65+  "progFile"
1838  7300               "s\0"
                         const [20]: "progFiles"
183A  04                 const type 4
183B  0E000000           string size (14)
183F  5370656369616C46+  "SpecialF"
1847  6F6C64657200       "older\0"
                         const [21]: "SpecialFolder"
184D  04                 const type 4
184E  0B000000           string size (11)
1852  666F6C6465725479+  "folderTy"
185A  706500             "pe\0"
                         const [22]: "folderType"
185D  04                 const type 4
185E  0D000000           string size (13)
1862  70726F6772616D46+  "programF"
186A  696C657300         "iles\0"
                         const [23]: "programFiles"
186F  04                 const type 4
1870  0C000000           string size (12)
1874  70726F6746696C65+  "progFile"
187C  733A2000           "s: \0"
                         const [24]: "progFiles: "
1880  04                 const type 4
1881  06000000           string size (6)
1885  7063616C6C00       "pcall"
                         const [25]: "pcall"
188B  04                 const type 4
188C  0B000000           string size (11)
1890  44656C6574654669+  "DeleteFi"
1898  6C6500             "le\0"
                         const [26]: "DeleteFile"
189B  04                 const type 4
189C  10000000           string size (16)
18A0  5C696E7374616C6C+  "\\install"
18A8  4C6F672E74787400   "Log.txt\0"
                         const [27]: "\\installLog.txt"
18B0  04                 const type 4
18B1  0A000000           string size (10)
18B5  4C6F63616C436F70+  "LocalCop"
18BD  7900               "y\0"
                         const [28]: "LocalCopy"
18BF  04                 const type 4
18C0  07000000           string size (7)
18C4  2E5C62696E5C00     ".\\bin\\"
                         const [29]: ".\\bin\\"
18CB  04                 const type 4
18CC  12000000           string size (18)
18D0  627374726170496E+  "bstrapIn"
18D8  7374616C6C2E6578+  "stall.ex"
18E0  6500               "e\0"
                         const [30]: "bstrapInstall.exe"
18E2  04                 const type 4
18E3  07000000           string size (7)
18E7  6C7561636F6D00     "luacom"
                         const [31]: "luacom"
18EE  04                 const type 4
18EF  0D000000           string size (13)
18F3  4372656174654F62+  "CreateOb"
18FB  6A65637400         "ject\0"
                         const [32]: "CreateObject"
1900  04                 const type 4
1901  16000000           string size (22)
1905  5374756262795574+  "StubbyUt"
190D  696C2E50726F6365+  "il.Proce"
1915  73734D677200       "ssMgr\0"
                         const [33]: "StubbyUtil.ProcessMgr"
191B  04                 const type 4
191C  13000000           string size (19)
1920  494E5354414C4C45+  "INSTALLE"
1928  525F4C4F43415449+  "R_LOCATI"
1930  4F4E00             "ON\0"
                         const [34]: "INSTALLER_LOCATION"
1933  04                 const type 4
1934  07000000           string size (7)
1938  737472696E6700     "string"
                         const [35]: "string"
193F  04                 const type 4
1940  05000000           string size (5)
1944  66696E6400         "find"
                         const [36]: "find"
1949  04                 const type 4
194A  04000000           string size (4)
194E  2E2A5C00           ".*\\"
                         const [37]: ".*\\"
1952  04                 const type 4
1953  04000000           string size (4)
1957  73756200           "sub"
                         const [38]: "sub"
195B  03                 const type 3
195C  000000000000F03F   const [39]: (1)
1964  04                 const type 4
1965  02000000           string size (2)
1969  2200               "\""
                         const [40]: "\""
196B  04                 const type 4
196C  1E000000           string size (30)
1970  5C62737472617049+  "\\bstrapI"
1978  6E7374616C6C2E65+  "nstall.e"
1980  78652220636C6561+  "xe\" clea"
1988  6E7570202200       "nup \"\0"
                         const [41]: "\\bstrapInstall.exe\" cleanup \""
198E  04                 const type 4
198F  07000000           string size (7)
1993  457865633A2000     "Exec: "
                         const [42]: "Exec: "
199A  04                 const type 4
199B  05000000           string size (5)
199F  4578656300         "Exec"
                         const [43]: "Exec"
19A4  04                 const type 4
19A5  01000000           string size (1)
19A9  00                 ""
                         const [44]: ""
19AA  04                 const type 4
19AB  27000000           string size (39)
19AF  4661696C65642074+  "Failed t"
19B7  6F20637265617465+  "o create"
19BF  2053747562627955+  " StubbyU"
19C7  74696C2E50726F63+  "til.Proc"
19CF  6573734D677200     "essMgr\0"
                         const [45]: "Failed to create StubbyUtil.ProcessMgr"
                         * functions:
19D6  00000000           sizep (0)
                         * code:
19DA  8D000000           sizecode (141)
19DE  04000000           [001] getupval   0   0        ; win32
19E2  863E0000           [002] gettable   0   0   250  ; "DeleteRegKey"
19E6  41000001           [003] loadk      1   1        ; "HKEY_CLASSES_ROOT"
19EA  81000002           [004] loadk      2   2        ; "Software\\.rgi"
19EE  59800100           [005] call       0   3   1  
19F2  C5000000           [006] getglobal  0   3        ; removeKnownStoreFronts
19F6  59800000           [007] call       0   1   1  
19FA  04000000           [008] getupval   0   0        ; win32
19FE  863F0000           [009] gettable   0   0   254  ; "RegDeleteTree"
1A02  41010001           [010] loadk      1   5        ; "HKEY_LOCAL_MACHINE"
1A06  81010002           [011] loadk      2   6        ; "SOFTWARE\\GameInstaller"
1A0A  59800100           [012] call       0   3   1  
1A0E  C5010000           [013] getglobal  0   7        ; io
1A12  86400000           [014] gettable   0   0   258  ; "write"
1A16  41020001           [015] loadk      1   9        ; "\n"
1A1A  85020002           [016] getglobal  2   10       ; os
1A1E  46410102           [017] gettable   2   2   261  ; "date"
1A22  01030003           [018] loadk      3   12       ; "%c "
1A26  99000102           [019] call       2   2   2  
1A2A  41030003           [020] loadk      3   13       ; "RemoveInstaller"
1A2E  59000200           [021] call       0   4   1  
1A32  C5030000           [022] getglobal  0   15       ; GetEnvironmentString
1A36  01040001           [023] loadk      1   16       ; "TEMP"
1A3A  99000100           [024] call       0   2   2  
1A3E  58000000           [025] test       0   0   1    ; to [27] if false
1A42  94008000           [026] jmp        3            ; to [30]
1A46  C5030000           [027] getglobal  0   15       ; GetEnvironmentString
1A4A  41040001           [028] loadk      1   17       ; "TMP"
1A4E  99000100           [029] call       0   2   2  
1A52  87030000           [030] setglobal  0   14       ; tmpDir
1A56  C5010000           [031] getglobal  0   7        ; io
1A5A  86400000           [032] gettable   0   0   258  ; "write"
1A5E  41020001           [033] loadk      1   9        ; "\n"
1A62  85020002           [034] getglobal  2   10       ; os
1A66  46410102           [035] gettable   2   2   261  ; "date"
1A6A  01030003           [036] loadk      3   12       ; "%c "
1A6E  99000102           [037] call       2   2   2  
1A72  81040003           [038] loadk      3   18       ; "tmpDir: "
1A76  C5040004           [039] getglobal  4   19       ; tostring
1A7A  85030005           [040] getglobal  5   14       ; tmpDir
1A7E  19000104           [041] call       4   2   0  
1A82  59000000           [042] call       0   0   1  
1A86  04000000           [043] getupval   0   0        ; win32
1A8A  C6430000           [044] gettable   0   0   271  ; "SpecialFolder"
1A8E  04000001           [045] getupval   1   0        ; win32
1A92  06C40001           [046] gettable   1   1   272  ; "folderType"
1A96  46C40001           [047] gettable   1   1   273  ; "programFiles"
1A9A  99000100           [048] call       0   2   2  
1A9E  07050000           [049] setglobal  0   20       ; progFiles
1AA2  C5010000           [050] getglobal  0   7        ; io
1AA6  86400000           [051] gettable   0   0   258  ; "write"
1AAA  41020001           [052] loadk      1   9        ; "\n"
1AAE  85020002           [053] getglobal  2   10       ; os
1AB2  46410102           [054] gettable   2   2   261  ; "date"
1AB6  01030003           [055] loadk      3   12       ; "%c "
1ABA  99000102           [056] call       2   2   2  
1ABE  01060003           [057] loadk      3   24       ; "progFiles: "
1AC2  C5040004           [058] getglobal  4   19       ; tostring
1AC6  05050005           [059] getglobal  5   20       ; progFiles
1ACA  19000104           [060] call       4   2   0  
1ACE  59000000           [061] call       0   0   1  
1AD2  45060000           [062] getglobal  0   25       ; pcall
1AD6  04000001           [063] getupval   1   0        ; win32
1ADA  06C50001           [064] gettable   1   1   276  ; "DeleteFile"
1ADE  85030002           [065] getglobal  2   14       ; tmpDir
1AE2  C1060003           [066] loadk      3   27       ; "\\installLog.txt"
1AE6  D3000102           [067] concat     2   2   3  
1AEA  59800100           [068] call       0   3   1  
1AEE  04000000           [069] getupval   0   0        ; win32
1AF2  86450000           [070] gettable   0   0   278  ; "LocalCopy"
1AF6  41070001           [071] loadk      1   29       ; ".\\bin\\"
1AFA  81070002           [072] loadk      2   30       ; "bstrapInstall.exe"
1AFE  93800001           [073] concat     1   1   2  
1B02  85030002           [074] getglobal  2   14       ; tmpDir
1B06  D9800100           [075] call       0   3   3  
1B0A  18000000           [076] test       0   0   0    ; to [78] if true
1B0E  140F8000           [077] jmp        61           ; to [139]
1B12  C5070002           [078] getglobal  2   31       ; luacom
1B16  86460102           [079] gettable   2   2   282  ; "CreateObject"
1B1A  41080003           [080] loadk      3   33       ; "StubbyUtil.ProcessMgr"
1B1E  99000102           [081] call       2   2   2  
1B22  18000102           [082] test       2   2   0    ; to [84] if true
1B26  540B8000           [083] jmp        46           ; to [130]
1B2A  04000003           [084] getupval   3   0        ; win32
1B2E  C6C30103           [085] gettable   3   3   271  ; "SpecialFolder"
1B32  04000004           [086] getupval   4   0        ; win32
1B36  06440204           [087] gettable   4   4   272  ; "folderType"
1B3A  46440204           [088] gettable   4   4   273  ; "programFiles"
1B3E  99000103           [089] call       3   2   2  
1B42  85080004           [090] getglobal  4   34       ; INSTALLER_LOCATION
1B46  13810103           [091] concat     3   3   4  
1B4A  C5080004           [092] getglobal  4   35       ; string
1B4E  86470204           [093] gettable   4   4   286  ; "find"
1B52  00800105           [094] move       5   3      
1B56  41090006           [095] loadk      6   37       ; ".*\\"
1B5A  D9800104           [096] call       4   3   3  
1B5E  C5080006           [097] getglobal  6   35       ; string
1B62  06480306           [098] gettable   6   6   288  ; "sub"
1B66  00800107           [099] move       7   3      
1B6A  00000208           [100] move       8   4      
1B6E  4DC80209           [101] sub        9   5   289  ; 1
1B72  99000206           [102] call       6   4   2  
1B76  00000303           [103] move       3   6      
1B7A  010A0006           [104] loadk      6   40       ; "\""
1B7E  85030007           [105] getglobal  7   14       ; tmpDir
1B82  410A0008           [106] loadk      8   41       ; "\\bstrapInstall.exe\" cleanup \""
1B86  00800109           [107] move       9   3      
1B8A  010A000A           [108] loadk      10  40       ; "\""
1B8E  93020306           [109] concat     6   6   10 
1B92  C5010007           [110] getglobal  7   7        ; io
1B96  86C00307           [111] gettable   7   7   258  ; "write"
1B9A  41020008           [112] loadk      8   9        ; "\n"
1B9E  85020009           [113] getglobal  9   10       ; os
1BA2  46C10409           [114] gettable   9   9   261  ; "date"
1BA6  0103000A           [115] loadk      10  12       ; "%c "
1BAA  99000109           [116] call       9   2   2  
1BAE  810A000A           [117] loadk      10  42       ; "Exec: "
1BB2  C504000B           [118] getglobal  11  19       ; tostring
1BB6  0000030C           [119] move       12  6      
1BBA  1900010B           [120] call       11  2   0  
1BBE  59000007           [121] call       7   0   1  
1BC2  4B490107           [122] self       7   2   293  ; "Exec"
1BC6  00000309           [123] move       9   6      
1BCA  010B000A           [124] loadk      10  44       ; ""
1BCE  0280000B           [125] loadbool   11  1   0    ; true
1BD2  0200000C           [126] loadbool   12  0   0    ; false
1BD6  0380060D           [127] loadnil    13  13     
1BDA  59800307           [128] call       7   7   1  
1BDE  14028000           [129] jmp        9            ; to [139]
1BE2  C5010003           [130] getglobal  3   7        ; io
1BE6  86C00103           [131] gettable   3   3   258  ; "write"
1BEA  41020004           [132] loadk      4   9        ; "\n"
1BEE  85020005           [133] getglobal  5   10       ; os
1BF2  46C10205           [134] gettable   5   5   261  ; "date"
1BF6  01030006           [135] loadk      6   12       ; "%c "
1BFA  99000105           [136] call       5   2   2  
1BFE  410B0006           [137] loadk      6   45       ; "Failed to create StubbyUtil.ProcessMgr"
1C02  59000203           [138] call       3   4   1  
1C06  C1090002           [139] loadk      2   39       ; 1
1C0A  1B000102           [140] return     2   2      
1C0E  1B800000           [141] return     0   1      
                         ** end of function **

                         * code:
1C12  9B000000           sizecode (155)
1C16  05000000           [001] getglobal  0   0        ; io
1C1A  C63E0000           [002] gettable   0   0   251  ; "output"
1C1E  05000001           [003] getglobal  1   0        ; io
1C22  06BF0001           [004] gettable   1   1   252  ; "open"
1C26  C1000002           [005] loadk      2   3        ; "..\\uninstLog.txt"
1C2A  01010003           [006] loadk      3   4        ; "a"
1C2E  19800101           [007] call       1   3   0  
1C32  59000000           [008] call       0   0   1  
1C36  45010000           [009] getglobal  0   5        ; dofile
1C3A  81010001           [010] loadk      1   6        ; "compat-5.1.lua"
1C3E  59000100           [011] call       0   2   1  
1C42  C5010000           [012] getglobal  0   7        ; require
1C46  01020001           [013] loadk      1   8        ; "luacom"
1C4A  59000100           [014] call       0   2   1  
1C4E  C5010000           [015] getglobal  0   7        ; require
1C52  41020001           [016] loadk      1   9        ; "rainstallerpaths"
1C56  59000100           [017] call       0   2   1  
1C5A  45010000           [018] getglobal  0   5        ; dofile
1C5E  81020001           [019] loadk      1   10       ; "config.lua"
1C62  59000100           [020] call       0   2   1  
1C66  45010000           [021] getglobal  0   5        ; dofile
1C6A  C1020001           [022] loadk      1   11       ; "blob"
1C6E  59000100           [023] call       0   2   1  
1C72  05000000           [024] getglobal  0   0        ; io
1C76  86410000           [025] gettable   0   0   262  ; "write"
1C7A  41030001           [026] loadk      1   13       ; "\n"
1C7E  85030002           [027] getglobal  2   14       ; os
1C82  46420102           [028] gettable   2   2   265  ; "date"
1C86  01040003           [029] loadk      3   16       ; "%c "
1C8A  99000102           [030] call       2   2   2  
1C8E  41040003           [031] loadk      3   17       ; "Loaded blob"
1C92  59000200           [032] call       0   4   1  
1C96  85040000           [033] getglobal  0   18       ; Win32Interop
1C9A  99800000           [034] call       0   1   2  
1C9E  22000001           [035] closure    1   0        ; 1 upvalues
1CA2  00000000           [036] move       0   0      
1CA6  C7040001           [037] setglobal  1   19       ; tryRemoveGamesRoot
1CAA  62000001           [038] closure    1   1        ; 1 upvalues
1CAE  00000000           [039] move       0   0      
1CB2  07050001           [040] setglobal  1   20       ; removeKnownStoreFronts
1CB6  A2000001           [041] closure    1   2        ; 1 upvalues
1CBA  00000000           [042] move       0   0      
1CBE  E2000002           [043] closure    2   3        ; 1 upvalues
1CC2  00000000           [044] move       0   0      
1CC6  85030003           [045] getglobal  3   14       ; os
1CCA  C6C30103           [046] gettable   3   3   271  ; "clock"
1CCE  99800003           [047] call       3   1   2  
1CD2  03000204           [048] loadnil    4   4      
1CD6  94028000           [049] jmp        11           ; to [61]
1CDA  06440005           [050] gettable   5   0   272  ; "Mutex"
1CDE  C1050006           [051] loadk      6   23       ; "RACV2InstallerInst"
1CE2  99000105           [052] call       5   2   2  
1CE6  00800204           [053] move       4   5      
1CEA  85030005           [054] getglobal  5   14       ; os
1CEE  C6C30205           [055] gettable   5   5   271  ; "clock"
1CF2  99800005           [056] call       5   1   2  
1CF6  CD800205           [057] sub        5   5   3  
1CFA  56018900           [058] lt         0   274 5    ; 60, to [60] if true
1CFE  14008000           [059] jmp        1            ; to [61]
1D02  54008000           [060] jmp        2            ; to [63]
1D06  18000204           [061] test       4   4   0    ; to [63] if true
1D0A  94FC7F00           [062] jmp        -13          ; to [50]
1D0E  05000005           [063] getglobal  5   0        ; io
1D12  86C10205           [064] gettable   5   5   262  ; "write"
1D16  41030006           [065] loadk      6   13       ; "\n"
1D1A  85030007           [066] getglobal  7   14       ; os
1D1E  46C20307           [067] gettable   7   7   265  ; "date"
1D22  01040008           [068] loadk      8   16       ; "%c "
1D26  99000107           [069] call       7   2   2  
1D2A  41060008           [070] loadk      8   25       ; "Running MrClean"
1D2E  59000205           [071] call       5   4   1  
1D32  18000204           [072] test       4   4   0    ; to [74] if true
1D36  14118000           [073] jmp        69           ; to [143]
1D3A  06450005           [074] gettable   5   0   276  ; "GetRegKeyValue"
1D3E  C1060006           [075] loadk      6   27       ; "HKEY_LOCAL_MACHINE"
1D42  01070007           [076] loadk      7   28       ; "SOFTWARE\\GameInstaller\\Installer"
1D46  41070008           [077] loadk      8   29       ; "Location"
1D4A  99000205           [078] call       5   4   2  
1D4E  18800205           [079] test       5   5   0    ; to [81] if true
1D52  14048000           [080] jmp        17           ; to [98]
1D56  15C60201           [081] eq         1   5   280  ; "", to [83] if false
1D5A  94038000           [082] jmp        15           ; to [98]
1D5E  C5070006           [083] getglobal  6   31       ; g_constants
1D62  49018D06           [084] settable   6   282 5    ; "installerLoc"
1D66  05000006           [085] getglobal  6   0        ; io
1D6A  86410306           [086] gettable   6   6   262  ; "write"
1D6E  41030007           [087] loadk      7   13       ; "\n"
1D72  85030008           [088] getglobal  8   14       ; os
1D76  46420408           [089] gettable   8   8   265  ; "date"
1D7A  01040009           [090] loadk      9   16       ; "%c "
1D7E  99000108           [091] call       8   2   2  
1D82  41080009           [092] loadk      9   33       ; "installerLoc: "
1D86  8508000A           [093] getglobal  10  34       ; tostring
1D8A  C507000B           [094] getglobal  11  31       ; g_constants
1D8E  86C6050B           [095] gettable   11  11  282  ; "installerLoc"
1D92  1900010A           [096] call       10  2   0  
1D96  59000006           [097] call       6   0   1  
1D9A  C5080006           [098] getglobal  6   35       ; pcall
1D9E  00800007           [099] move       7   1      
1DA2  D9000106           [100] call       6   2   3  
1DA6  18000306           [101] test       6   6   0    ; to [103] if true
1DAA  14018000           [102] jmp        5            ; to [108]
1DAE  C5080008           [103] getglobal  8   35       ; pcall
1DB2  00000109           [104] move       9   2      
1DB6  D9000108           [105] call       8   2   3  
1DBA  00800407           [106] move       7   9      
1DBE  00000406           [107] move       6   8      
1DC2  58000306           [108] test       6   6   1    ; to [110] if false
1DC6  D4058000           [109] jmp        24           ; to [134]
1DCA  05090008           [110] getglobal  8   36       ; ErrorHandler
1DCE  99800008           [111] call       8   1   2  
1DD2  05000009           [112] getglobal  9   0        ; io
1DD6  86C10409           [113] gettable   9   9   262  ; "write"
1DDA  4109000A           [114] loadk      10  37       ; "\nUninstallation Failed!!!, "
1DDE  8508000B           [115] getglobal  11  34       ; tostring
1DE2  0080030C           [116] move       12  7      
1DE6  1900010B           [117] call       11  2   0  
1DEA  59000009           [118] call       9   0   1  
1DEE  06480009           [119] gettable   9   0   288  ; "LogMessage"
1DF2  8503000A           [120] getglobal  10  14       ; os
1DF6  4642050A           [121] gettable   10  10  265  ; "date"
1DFA  0104000B           [122] loadk      11  16       ; "%c "
1DFE  9900010A           [123] call       10  2   2  
1E02  C109000B           [124] loadk      11  39       ; "Uninstallation Failed!!!, "
1E06  8508000C           [125] getglobal  12  34       ; tostring
1E0A  0080030D           [126] move       13  7      
1E0E  9900010C           [127] call       12  2   2  
1E12  1303050A           [128] concat     10  10  12 
1E16  59000109           [129] call       9   2   1  
1E1A  86480409           [130] gettable   9   8   290  ; "HandleError"
1E1E  0080030A           [131] move       10  7      
1E22  59000109           [132] call       9   2   1  
1E26  D4008000           [133] jmp        4            ; to [138]
1E2A  05000008           [134] getglobal  8   0        ; io
1E2E  86410408           [135] gettable   8   8   262  ; "write"
1E32  410A0009           [136] loadk      9   41       ; "\nUninstallation Complete!"
1E36  59000108           [137] call       8   2   1  
1E3A  06490208           [138] gettable   8   4   292  ; "Release"
1E3E  59800008           [139] call       8   1   1  
1E42  46490208           [140] gettable   8   4   293  ; "Close"
1E46  59800008           [141] call       8   1   1  
1E4A  D4028000           [142] jmp        12           ; to [155]
1E4E  05000005           [143] getglobal  5   0        ; io
1E52  86C10205           [144] gettable   5   5   262  ; "write"
1E56  010B0006           [145] loadk      6   44       ; "\nUnable to obtain mutex. Couldn't uninstall clientless files."
1E5A  59000105           [146] call       5   2   1  
1E5E  06480005           [147] gettable   5   0   288  ; "LogMessage"
1E62  85030006           [148] getglobal  6   14       ; os
1E66  46420306           [149] gettable   6   6   265  ; "date"
1E6A  01040007           [150] loadk      7   16       ; "%c "
1E6E  99000106           [151] call       6   2   2  
1E72  410B0007           [152] loadk      7   45       ; "Unable to obtain RACV2InstallerInst mutex. Couldn't uninstall clientless files."
1E76  D3010306           [153] concat     6   6   7  
1E7A  59000105           [154] call       5   2   1  
1E7E  1B800000           [155] return     0   1      
                         ** end of function **

1E82                     ** end of chunk **
